industry11_090319.py
industry-1.0.0.dist-info/METADATA
industry-1.0.0.dist-info/WHEEL
industry-1.0.0.dist-info/top_level.txt
industry-1.0.0.dist-info/RECORD
