Metadata-Version: 2.1
Name: industry
Version: 1.0.0
Summary: first dist
Home-page: https://www.python.org/sigs/distutils-sig/
Author: shm
Author-email: UNKNOWN
License: UNKNOWN
Platform: UNKNOWN
